{
  "tempo_bpm": 240,
  "audio": {
    "waveform": "sine",
    "sample_rate_hz": 44100,
    "volume": 0.76,
    "fade_ms": 4,
    "harmonics": [
      1.0,
      0.28,
      0.1
    ]
  },
  "midi": {
    "channel": 0,
    "program": 80,
    "velocity": 98
  },
  "events": [
    {
      "rest_beats": 0.25
    },
    {
      "note": "A4",
      "beats": 0.25,
      "velocity": 126
    },
    {
      "rest_beats": 0.25
    },
    {
      "note": "C5",
      "beats": 0.25,
      "velocity": 122
    },
    {
      "rest_beats": 0.25
    },
    {
      "note": "E5",
      "beats": 0.25,
      "velocity": 124
    },
    {
      "rest_beats": 0.25
    },
    {
      "note": "A5",
      "beats": 0.25,
      "velocity": 120
    },
    {
      "rest_beats": 2.0
    }
  ]
}
